linkedin_games_scraper/__init__.py
linkedin_games_scraper/__main__.py
linkedin_games_scraper/solver.py
linkedin_games_scraper-0.2.0.dist-info/licenses/LICENSE
tests/__init__.py
tests/test_basic.py
linkedin_games_scraper-0.2.0.dist-info/METADATA
linkedin_games_scraper-0.2.0.dist-info/WHEEL
linkedin_games_scraper-0.2.0.dist-info/entry_points.txt
linkedin_games_scraper-0.2.0.dist-info/top_level.txt
linkedin_games_scraper-0.2.0.dist-info/RECORD
