Metadata-Version: 2.4
Name: linkedin_games_scraper
Version: 0.2.0
Summary: A package to solve LinkedIn games by extracting solutions
Home-page: https://github.com/sebtheo/linkedin-games-scraper
Author: LinkedIn Games Scraper
Author-email: seb@theo4.uk
Classifier: Programming Language :: Python :: 3
Classifier: License :: OSI Approved :: GNU Affero General Public License v3
Classifier: Operating System :: OS Independent
Requires-Python: >=3.6
License-File: LICENSE
Requires-Dist: selenium-wire>=5.1.0
Requires-Dist: selenium>=4.0.0
Requires-Dist: blinker==1.7
Requires-Dist: setuptools>=69.0.3
Provides-Extra: dev
Requires-Dist: pytest>=7.0.0; extra == "dev"
Requires-Dist: ruff>=0.1.0; extra == "dev"
Requires-Dist: build>=0.10.0; extra == "dev"
Requires-Dist: twine>=4.0.0; extra == "dev"
Requires-Dist: pre-commit>=3.0.0; extra == "dev"
Dynamic: author
Dynamic: author-email
Dynamic: classifier
Dynamic: description
Dynamic: description-content-type
Dynamic: home-page
Dynamic: license-file
Dynamic: provides-extra
Dynamic: requires-dist
Dynamic: requires-python
Dynamic: summary
